owldata/__init__.py
owldata/__version__.py
owldata/_owlerror.py
owldata/_owltime.py
owldata/api.py
owldata/config.py
owldata-0.0.18.dist-info/LICENSE
owldata-0.0.18.dist-info/METADATA
owldata-0.0.18.dist-info/WHEEL
owldata-0.0.18.dist-info/top_level.txt
owldata-0.0.18.dist-info/RECORD
