Metadata-Version: 2.1
Name: owldata
Version: 0.0.18
Summary: Testing version
Home-page: https://owl.cmoney.com.tw/Owl/
Author: Owl Corp.
Author-email: owldb@cmoney.com.tw
License: MIT
Keywords: cmoney,financial data,owldata
Platform: UNKNOWN
Requires-Dist: pandas (>=0.14)
Requires-Dist: numpy (>=1.8)
Requires-Dist: requests (>=2.7.0)
